pyramid_fullauth/__init__.py
pyramid_fullauth/auth.py
pyramid_fullauth/events.py
pyramid_fullauth/exceptions.py
pyramid_fullauth/request.py
pyramid_fullauth/security.py
pyramid_fullauth/tools.py
pyramid_fullauth/models/__init__.py
pyramid_fullauth/models/extensions/__init__.py
pyramid_fullauth/models/mixins/__init__.py
pyramid_fullauth/models/mixins/email.py
pyramid_fullauth/models/mixins/password.py
pyramid_fullauth/routing/__init__.py
pyramid_fullauth/routing/predicates.py
pyramid_fullauth/views/__init__.py
pyramid_fullauth/views/social.py
pyramid_fullauth/views/basic/__init__.py
pyramid_fullauth/views/basic/activate.py
pyramid_fullauth/views/basic/forbidden.py
pyramid_fullauth/views/basic/login.py
pyramid_fullauth/views/basic/logout.py
pyramid_fullauth/views/basic/register.py
pyramid_fullauth/views/basic/profile/__init__.py
pyramid_fullauth/views/basic/profile/email.py
pyramid_fullauth/views/basic/profile/password.py
pyramid_fullauth-2.2.0.dist-info/licenses/AUTHORS.rst
pyramid_fullauth-2.2.0.dist-info/licenses/LICENSE
pyramid_fullauth-2.2.0.dist-info/METADATA
pyramid_fullauth-2.2.0.dist-info/WHEEL
pyramid_fullauth-2.2.0.dist-info/top_level.txt
pyramid_fullauth-2.2.0.dist-info/zip-safe
pyramid_fullauth-2.2.0.dist-info/RECORD
