Metadata-Version: 2.4
Name: pyramid_fullauth
Version: 2.2.0
Summary: pyramid_fullauth provides full authentication / authorisation implementation for pyramid applications
Author-email: Grzegorz Śliwiński <fizyk+pypi@fizyk.dev>
License: The MIT License (MIT): http://opensource.org/licenses/MIT
Project-URL: Source, https://github.com/fizyk/pyramid_fullauth/
Project-URL: Bug Tracker, https://github.com/fizyk/pyramid_fullauth/issues
Project-URL: Changelog, https://github.com/fizyk/pyramid_fullauth/blob/v2.2.0/CHANGES.rst
Project-URL: Documentation, https://fizyk.dev/pyramid_fullauth/
Keywords: pyramid,authentication,authorisation,user
Classifier: Development Status :: 5 - Production/Stable
Classifier: Environment :: Web Environment
Classifier: Intended Audience :: Developers
Classifier: License :: OSI Approved :: MIT License
Classifier: Natural Language :: English
Classifier: Operating System :: OS Independent
Classifier: Programming Language :: Python
Classifier: Programming Language :: Python :: 3
Classifier: Programming Language :: Python :: 3.10
Classifier: Programming Language :: Python :: 3.11
Classifier: Programming Language :: Python :: 3.12
Classifier: Programming Language :: Python :: 3.13
Classifier: Programming Language :: Python :: 3.14
Classifier: Framework :: Pyramid
Classifier: Topic :: Database :: Front-Ends
Classifier: Topic :: Internet :: WWW/HTTP
Classifier: Topic :: Internet :: WWW/HTTP :: WSGI
Classifier: Topic :: Software Development :: Libraries :: Python Modules
Requires-Python: >=3.10
License-File: LICENSE
License-File: AUTHORS.rst
Requires-Dist: pyramid>=2
Requires-Dist: pyramid_basemodel>=0.3
Requires-Dist: pyramid_mako
Requires-Dist: pyramid_localize
Requires-Dist: SQLAlchemy>=1.3.0
Requires-Dist: velruse>=1.1.1
Provides-Extra: docs
Requires-Dist: sphinx; extra == "docs"
Dynamic: license-file
